ocrd_doxa/__init__.py
ocrd_doxa/cli.py
ocrd_doxa/config.py
ocrd_doxa/doxa_binarize.py
ocrd_doxa/ocrd-tool.json
ocrd_doxa-0.0.2.dist-info/LICENSE
ocrd_doxa-0.0.2.dist-info/METADATA
ocrd_doxa-0.0.2.dist-info/WHEEL
ocrd_doxa-0.0.2.dist-info/entry_points.txt
ocrd_doxa-0.0.2.dist-info/top_level.txt
ocrd_doxa-0.0.2.dist-info/RECORD
