Metadata-Version: 2.1
Name: ocrd-doxa
Version: 0.0.2
Summary: OCR-D wrapper for DoxaPy image binarization via locally adaptive thresholding
Home-page: https://github.com/bertsky/ocrd_doxa
Author: Robert Sachunsky
Author-email: sachunsky@informatik.uni-leipzig.de
License: MIT
Platform: UNKNOWN
License-File: LICENSE
Requires-Dist: ocrd (>=2.13)
Requires-Dist: click (>=7.0)
Requires-Dist: numpy (>=1.17.0)
Requires-Dist: pillow (>=7.1.2)
Requires-Dist: doxapy (>=0.9.1)
